idcrockford/__init__.py
idcrockford/__main__.py
idcrockford/py.typed
idcrockford-0.1.2.dist-info/entry_points.txt
idcrockford-0.1.2.dist-info/WHEEL
idcrockford-0.1.2.dist-info/METADATA
idcrockford-0.1.2.dist-info/RECORD
