Metadata-Version: 2.3
Name: idcrockford
Version: 0.1.2
Summary: Crockford Base32 ID generation and validation
Author-email: saif <sirsaif99@gmail.com>
Requires-Python: >=3.12
